chaospy/__init__.py
chaospy/regression.py
chaospy/saltelli.py
chaospy/spectral.py
chaospy/descriptives/__init__.py
chaospy/descriptives/conditional.py
chaospy/descriptives/covariance.py
chaospy/descriptives/expected.py
chaospy/descriptives/kurtosis.py
chaospy/descriptives/percentile.py
chaospy/descriptives/quantity_of_interest.py
chaospy/descriptives/skewness.py
chaospy/descriptives/standard_deviation.py
chaospy/descriptives/variance.py
chaospy/descriptives/correlation/__init__.py
chaospy/descriptives/correlation/auto_correlation.py
chaospy/descriptives/correlation/pearson.py
chaospy/descriptives/correlation/spearman.py
chaospy/descriptives/sensitivity/__init__.py
chaospy/descriptives/sensitivity/main.py
chaospy/descriptives/sensitivity/main2.py
chaospy/descriptives/sensitivity/total.py
chaospy/distributions/__init__.py
chaospy/distributions/approximation.py
chaospy/distributions/baseclass/__init__.py
chaospy/distributions/baseclass/copula.py
chaospy/distributions/baseclass/distribution.py
chaospy/distributions/baseclass/lower_upper.py
chaospy/distributions/baseclass/mean_covariance.py
chaospy/distributions/baseclass/operator.py
chaospy/distributions/baseclass/shift_scale.py
chaospy/distributions/baseclass/simple.py
chaospy/distributions/baseclass/slice_.py
chaospy/distributions/baseclass/user.py
chaospy/distributions/baseclass/utils.py
chaospy/distributions/collection/__init__.py
chaospy/distributions/collection/alpha.py
chaospy/distributions/collection/anglit.py
chaospy/distributions/collection/beta.py
chaospy/distributions/collection/binomial.py
chaospy/distributions/collection/bradford.py
chaospy/distributions/collection/burr.py
chaospy/distributions/collection/cauchy.py
chaospy/distributions/collection/chi.py
chaospy/distributions/collection/chi_squared.py
chaospy/distributions/collection/discrete_uniform.py
chaospy/distributions/collection/double_gamma.py
chaospy/distributions/collection/double_weibull.py
chaospy/distributions/collection/exponential_power.py
chaospy-4.3.21.dist-info/licenses/LICENSE.txt
chaospy-4.3.21.dist-info/METADATA
chaospy-4.3.21.dist-info/WHEEL
chaospy-4.3.21.dist-info/top_level.txt
chaospy-4.3.21.dist-info/RECORD
