Metadata-Version: 2.4
Name: chaospy
Version: 4.3.21
Summary: Numerical tool for performing uncertainty quantification
License: MIT license
Classifier: Development Status :: 5 - Production/Stable
Classifier: Intended Audience :: Science/Research
Classifier: Topic :: Scientific/Engineering :: Mathematics
Classifier: Natural Language :: English
Requires-Python: >=3.9
License-File: LICENSE.txt
Requires-Dist: numpy>=1.20
Requires-Dist: numpoly>=1.2.12
Requires-Dist: scipy
Requires-Dist: setuptools>=40.9.0
Requires-Dist: importlib-metadata; python_version < "3.10"
Provides-Extra: dev
Requires-Dist: openturns==1.23; extra == "dev"
Requires-Dist: scikit-learn; extra == "dev"
Requires-Dist: gstools; extra == "dev"
Requires-Dist: jupyter; extra == "dev"
Requires-Dist: matplotlib; extra == "dev"
Requires-Dist: nbsphinx; extra == "dev"
Requires-Dist: sphinxcontrib-bibtex; extra == "dev"
Requires-Dist: black==22.10.0; extra == "dev"
Requires-Dist: pandoc; extra == "dev"
Requires-Dist: pylint==2.15.5; extra == "dev"
Requires-Dist: pydocstyle==3.0.0; extra == "dev"
Requires-Dist: pydata_sphinx_theme==0.11.0; extra == "dev"
Requires-Dist: sympy; extra == "dev"
Requires-Dist: pytest; extra == "dev"
Requires-Dist: pytest-cov; extra == "dev"
Requires-Dist: codecov; extra == "dev"
Requires-Dist: coverage>=5.0; extra == "dev"
Requires-Dist: Sphinx; extra == "dev"
Requires-Dist: sphinx_automodapi; extra == "dev"
Requires-Dist: build; extra == "dev"
Requires-Dist: twine; extra == "dev"
Dynamic: license-file
